flask_supabase/__init__.py
flask_supabase-0.2.0.dist-info/LICENSE
flask_supabase-0.2.0.dist-info/WHEEL
flask_supabase-0.2.0.dist-info/METADATA
flask_supabase-0.2.0.dist-info/RECORD
